odoo/addons/stock_release_channel_shipment_advice_process_end_time/README.rst
odoo/addons/stock_release_channel_shipment_advice_process_end_time/__init__.py
odoo/addons/stock_release_channel_shipment_advice_process_end_time/__manifest__.py
odoo/addons/stock_release_channel_shipment_advice_process_end_time/i18n/fr_BE.po
odoo/addons/stock_release_channel_shipment_advice_process_end_time/i18n/it.po
odoo/addons/stock_release_channel_shipment_advice_process_end_time/i18n/stock_release_channel_shipment_advice_process_end_time.pot
odoo/addons/stock_release_channel_shipment_advice_process_end_time/models/__init__.py
odoo/addons/stock_release_channel_shipment_advice_process_end_time/models/stock_release_channel.py
odoo/addons/stock_release_channel_shipment_advice_process_end_time/models/stock_warehouse.py
odoo/addons/stock_release_channel_shipment_advice_process_end_time/readme/CONTRIBUTORS.rst
odoo/addons/stock_release_channel_shipment_advice_process_end_time/readme/DESCRIPTION.rst
odoo/addons/stock_release_channel_shipment_advice_process_end_time/readme/USAGE.rst
odoo/addons/stock_release_channel_shipment_advice_process_end_time/static/description/icon.png
odoo/addons/stock_release_channel_shipment_advice_process_end_time/static/description/index.html
odoo/addons/stock_release_channel_shipment_advice_process_end_time/tests/__init__.py
odoo/addons/stock_release_channel_shipment_advice_process_end_time/tests/test_stock_release_channel_shipment_advice_process_end_time.py
odoo/addons/stock_release_channel_shipment_advice_process_end_time/views/stock_release_channel.xml
odoo/addons/stock_release_channel_shipment_advice_process_end_time/views/stock_warehouse.xml
odoo/addons/stock_release_channel_shipment_advice_process_end_time/wizards/__init__.py
odoo/addons/stock_release_channel_shipment_advice_process_end_time/wizards/shipment_advice_planner.py
odoo_addon_stock_release_channel_shipment_advice_process_end_time-16.0.1.0.0.3.dist-info/METADATA
odoo_addon_stock_release_channel_shipment_advice_process_end_time-16.0.1.0.0.3.dist-info/WHEEL
odoo_addon_stock_release_channel_shipment_advice_process_end_time-16.0.1.0.0.3.dist-info/top_level.txt
odoo_addon_stock_release_channel_shipment_advice_process_end_time-16.0.1.0.0.3.dist-info/RECORD
